README.rst
setup.cfg
setup.py
python_demo_pkg.egg-info/PKG-INFO
python_demo_pkg.egg-info/SOURCES.txt
python_demo_pkg.egg-info/dependency_links.txt
python_demo_pkg.egg-info/requires.txt
python_demo_pkg.egg-info/top_level.txt
sub_pkg_demo/__init__.py
sub_pkg_demo/demo.py
test/__init__.py
test/test_one.py