Metadata-Version: 1.0
Name: python-demo-pkg
Version: 0.1
Summary: This is an Example Package
Home-page: http://crocker-webapps.com
Author: David Crocker
Author-email: dwcrocker@outlook.com
License: MIT
Keywords: mydemo example
Platform: UNKNOWN
